scripts/__init__.py
scripts/clustering_3d.code-workspace
scripts/globals.py
scripts/main.py
scripts/datasets/__init__.py
scripts/datasets/af_merge.py
scripts/datasets/build_datasets.py
scripts/datasets/custom_pdb.py
scripts/datasets/get_pae.py
scripts/datasets/get_structures.py
scripts/datasets/model_confidence.py
scripts/datasets/parse_pae.py
scripts/datasets/prob_contact_maps.py
scripts/datasets/seq_for_mut_prob.py
scripts/datasets/utils.py
scripts/plotting/__init__.py
scripts/plotting/build_annotations.py
scripts/plotting/chimerax_plot.py
scripts/plotting/pdb_tool.py
scripts/plotting/pfam.py
scripts/plotting/plot.py
scripts/plotting/stability_change.py
scripts/plotting/uniprot_feat.py
scripts/plotting/utils.py
scripts/run/__init__.py
scripts/run/clustering.py
scripts/run/communities.py
scripts/run/miss_mut_prob.py
scripts/run/mutability.py
scripts/run/pvalues.py
scripts/run/score_and_simulations.py
scripts/run/utils.py
oncodrive3d-1.0.7.dist-info/METADATA
oncodrive3d-1.0.7.dist-info/WHEEL
oncodrive3d-1.0.7.dist-info/entry_points.txt
oncodrive3d-1.0.7.dist-info/licenses/LICENSE
oncodrive3d-1.0.7.dist-info/RECORD
