Metadata-Version: 2.4
Name: Oncodrive3D
Version: 1.0.7
Summary: Oncodrive3D is a method designed to analyse patterns of somatic mutations across tumors to identify three-dimensional (3D) clusters of missense mutations and detect genes that are under positive selection.
Project-URL: Homepage, https://github.com/bbglab/clustering_3d
Project-URL: Repository, https://github.com/bbglab/clustering_3d
Project-URL: Issues, https://github.com/bbglab/clustering_3d/issues
Author-email: "BBGLab (Barcelona Biomedical Genomics Lab)" <bbglab@irbbarcelona.org>, Stefano Pellegrini <stefano.pellegrini@irbbarcelona.org>
License: GNU Affero General Public License v3 or later (AGPLv3+)
License-File: LICENSE
Keywords: bbglab,bioinformatics,driversprediction,positiveselection
Requires-Python: >=3.10
Requires-Dist: adjusttext==1.1.1
Requires-Dist: aiohttp>=3.11.10
Requires-Dist: bgreference==0.7
Requires-Dist: bio==1.7.1
Requires-Dist: colorcet==3.0.1
Requires-Dist: daiquiri>=3.3.0
Requires-Dist: matplotlib>=3.6.2
Requires-Dist: networkx==2.7.1
Requires-Dist: numpy==1.26.4
Requires-Dist: pandas==1.4.2
Requires-Dist: progressbar2==4.0.0
Requires-Dist: pypdl==1.4.5
Requires-Dist: pytabix==0.0.2
Requires-Dist: scikit-learn>=1.3.0
Requires-Dist: scipy>=1.7.3
Requires-Dist: seaborn>=0.12.2
Requires-Dist: setuptools==61.2.0
Requires-Dist: statsmodels>=0.13.2
Requires-Dist: tqdm>=4.67.1
Provides-Extra: linting
Requires-Dist: ruff>=0.8.3; extra == 'linting'
